gaussian_distributions_kueen/Binomialdistribution.py
gaussian_distributions_kueen/Gaussiandistribution.py
gaussian_distributions_kueen/Generaldistribution.py
gaussian_distributions_kueen/__init__.py
gaussian_distributions_kueen-0.1.dist-info/LICENSE
gaussian_distributions_kueen-0.1.dist-info/METADATA
gaussian_distributions_kueen-0.1.dist-info/WHEEL
gaussian_distributions_kueen-0.1.dist-info/top_level.txt
gaussian_distributions_kueen-0.1.dist-info/RECORD
