Metadata-Version: 2.1
Name: gaussian-distributions-kueen
Version: 0.1
Summary: Gaussian and Binomial distributions
Home-page: UNKNOWN
Author: Keshvi Gupta
Author-email: keshvi2298@gmail.com
License: UNKNOWN
Platform: UNKNOWN
Classifier: Programming Language :: Python :: 3
Classifier: License :: OSI Approved :: MIT License
Classifier: Operating System :: OS Independent
